{
  "menu": [
    {
      "id_menu": 1,
      "fecha": "2024-08-21",
      "desayuno": {
        "id_desayuno": 1,
        "bebible": "harina con cañiwa, tarwi",
        "acompaniamiento": "pan con huevo, aceituna",
        "aditivo": null,
        "fruta_postre": null,
        "image_url": "https://picsum.photos/200/300?grayscale",
        "carbohidratos": 70,
        "proteinas": 19,
        "grasas": 10
      },
      "almuerzo": {
        "id_almuerzo": 1,
        "sopa_entrada": "crema de arvejas",
        "segundo": "pachamanca de pollo a la olla, camote, papa",
        "ensalada": "crema pachamanquera",
        "fruta": "mandarina",
        "postre": null,
        "refresco": "cebada",
        "image_url": "https://picsum.photos/seed/picsum/200/300",
        "carbohidratos": 95,
        "proteinas": 35,
        "grasas": 22
      },
      "cena": {
        "id_cena": 1,
        "plato_principal": "arroz con perejil y carne",
        "postre": "cochinito",
        "bebida": "infusión",
        "image_url": "https://picsum.photos/200/300/?blur",
        "carbohidratos": 80,
        "proteinas": 26,
        "grasas": 14
      }
    },
    {
      "id_menu": 2,
      "fecha": "2024-08-22",
      "desayuno": {
        "id_desayuno": 2,
        "bebible": "harina de 7 semillas, maca, leche",
        "acompaniamiento": "ensalada de fideos con atún",
        "aditivo": null,
        "fruta_postre": null,
        "image_url": "https://picsum.photos/200/300?grayscale",
        "carbohidratos": 72,
        "proteinas": 20,
        "grasas": 12
      },
      "almuerzo": {
        "id_almuerzo": 2,
        "sopa_entrada": "sopa de morón",
        "segundo": "res al imentón, arroz",
        "ensalada": "criolla",
        "fruta": null,
        "postre": "flan",
        "refresco": "cocona",
        "image_url": "https://picsum.photos/seed/picsum/200/300",
        "carbohidratos": 90,
        "proteinas": 35,
        "grasas": 18
      },
      "cena": {
        "id_cena": 2,
        "plato_principal": "coliflor con pollo, arroz",
        "postre": "mazamorra de maíz",
        "bebida": "infusión",
        "image_url": "https://picsum.photos/200/300/?blur",
        "carbohidratos": 70,
        "proteinas": 24,
        "grasas": 13
      }
    },
    {
      "id_menu": 3,
      "fecha": "2024-08-23",
      "desayuno": {
        "id_desayuno": 3,
        "bebible": "Harian de quinua, lúcuma, leche",
        "acompaniamiento": "pan con palta y huevo",
        "aditivo": null,
        "fruta_postre": "papaya",
        "image_url": "https://picsum.photos/200/300?grayscale",
        "carbohidratos": 70,
        "proteinas": 19,
        "grasas": 11
      },
      "almuerzo": {
        "id_almuerzo": 3,
        "sopa_entrada": "crema de garbanzos",
        "segundo": "carapulcra con sopa seca con chancho",
        "ensalada": null,
        "fruta": "pera",
        "postre": null,
        "refresco": "manzana",
        "image_url": "https://picsum.photos/seed/picsum/200/300",
        "carbohidratos": 97,
        "proteinas": 34,
        "grasas": 25
      },
      "cena": {
        "id_cena": 3,
        "plato_principal": "migadito con mondongo",
        "postre": "mazamorra de manzana",
        "bebida": "infusión",
        "image_url": "https://picsum.photos/200/300/?blur",
        "carbohidratos": 72,
        "proteinas": 25,
        "grasas": 15
      }
    },
    {
      "id_menu": 4,
      "fecha": "2024-08-24",
      "desayuno": {
        "id_desayuno": 4,
        "bebible": "Harian de quinua, lúcuma, leche",
        "acompaniamiento": "pan con palta y huevo",
        "aditivo": null,
        "fruta_postre": "papaya",
        "image_url": "https://picsum.photos/200/300?grayscale",
        "carbohidratos": 70,
        "proteinas": 19,
        "grasas": 11
      },
      "almuerzo": {
        "id_almuerzo": 4,
        "sopa_entrada": "chílcano",
        "segundo": "ceviche de pescado, camote, cancah serrana",
        "ensalada": null,
        "fruta": "plátano",
        "postre": null,
        "refresco": "carambola",
        "image_url": "https://picsum.photos/seed/picsum/200/300",
        "carbohidratos": 78,
        "proteinas": 36,
        "grasas": 15
      },
      "cena": null
    }
  ]
}
